cej_utils/__init__.py
cej_utils/calc_cej.py
cej_utils/cej_calculations.py
cej_utils/closest_enamel_bone_pairs.py
cej_utils/is_close_pairing.py
cej_utils-0.0.4.dist-info/ccc/__init__.py
cej_utils-0.0.4.dist-info/ccc/calc_cej.py
cej_utils-0.0.4.dist-info/ccc/cej_calculations.py
cej_utils-0.0.4.dist-info/ccc/closest_enamel_bone_pairs.py
cej_utils-0.0.4.dist-info/ccc/is_close_pairing.py
cej_utils-0.0.4.dist-info/ccc/__pycache__/__init__.cpython-37.pyc
cej_utils-0.0.4.dist-info/ccc/__pycache__/calc_cej.cpython-37.pyc
cej_utils-0.0.4.dist-info/ccc/__pycache__/cej_calculations.cpython-37.pyc
cej_utils-0.0.4.dist-info/ccc/__pycache__/closest_enamel_bone_pairs.cpython-37.pyc
cej_utils-0.0.4.dist-info/ccc/__pycache__/is_close_pairing.cpython-37.pyc
cej_utils-0.0.4.dist-info/LICENSE
cej_utils-0.0.4.dist-info/METADATA
cej_utils-0.0.4.dist-info/WHEEL
cej_utils-0.0.4.dist-info/top_level.txt
cej_utils-0.0.4.dist-info/RECORD
