Metadata-Version: 2.1
Name: cej-utils
Version: 0.0.4
Summary: Bundle of functions to help calculate various metrics.
Home-page: https://github.com/overjetdental/cej-utils
Author: Overjet AI
Author-email: caidan@overjet.ai
License: UNKNOWN
Platform: UNKNOWN
Classifier: Programming Language :: Python :: 3
Classifier: License :: OSI Approved :: MIT License
Classifier: Operating System :: OS Independent
Requires-Python: >=3.6
Requires-Dist: imantics (>=0.1.12)
Requires-Dist: numpy (>=1.18.1)
Requires-Dist: Shapely (==1.7.0)
